{
  "date": "2026-06-30",
  "picks": [
    {
      "prop_type": "K",
      "name": "Justin Wrobleski",
      "team": "LAD",
      "opp": "OAK",
      "line": 5.5,
      "pick": "under",
      "odds": "+115",
      "model": 4.5,
      "edge_val": 0.2348,
      "book": "DraftKings",
      "time": "2026-07-01T01:40:00Z"
    },
    {
      "prop_type": "K",
      "name": "Landen Roupp",
      "team": "SFG",
      "opp": "ARI",
      "line": 4.5,
      "pick": "over",
      "odds": "-170",
      "model": 5.5,
      "edge_val": 0.0567,
      "book": "Kalshi",
      "time": "2026-07-01T01:40:00Z"
    },
    {
      "prop_type": "HR",
      "name": "Liam Hicks",
      "opp_pitcher": "Tanner Gordon",
      "team": "MIA",
      "opp": "COL",
      "home": "COL",
      "away": "MIA",
      "line": 0.5,
      "pick": "yes",
      "odds": "+2400",
      "model": 0.2235,
      "edge_val": 0.1839,
      "book": "Kalshi",
      "time": "2026-07-01T00:40:00Z"
    },
    {
      "prop_type": "HR",
      "name": "Kody Clemens",
      "opp_pitcher": "Mike Burrows",
      "team": "MIN",
      "opp": "HOU",
      "home": "HOU",
      "away": "MIN",
      "line": 0.5,
      "pick": "yes",
      "odds": "+1567",
      "model": 0.2413,
      "edge_val": 0.183,
      "book": "Kalshi",
      "time": "2026-07-01T00:10:00Z"
    },
    {
      "prop_type": "HR",
      "name": "Ryan Kreidler",
      "opp_pitcher": "Mike Burrows",
      "team": "MIN",
      "opp": "HOU",
      "home": "HOU",
      "away": "MIN",
      "line": 0.5,
      "pick": "yes",
      "odds": "+1900",
      "model": 0.1821,
      "edge_val": 0.1331,
      "book": "Kalshi",
      "time": "2026-07-01T00:10:00Z"
    },
    {
      "prop_type": "HR",
      "name": "Cole Carrigg",
      "opp_pitcher": "Eury P\u00e9rez",
      "team": "COL",
      "opp": "MIA",
      "home": "COL",
      "away": "MIA",
      "line": 0.5,
      "pick": "yes",
      "odds": "+1150",
      "model": 0.2082,
      "edge_val": 0.132,
      "book": "Kalshi",
      "time": "2026-07-01T00:40:00Z"
    },
    {
      "prop_type": "HR",
      "name": "Christian Walker",
      "opp_pitcher": "Joe Ryan",
      "team": "HOU",
      "opp": "MIN",
      "home": "HOU",
      "away": "MIN",
      "line": 0.5,
      "pick": "yes",
      "odds": "+2400",
      "model": 0.17,
      "edge_val": 0.1304,
      "book": "Kalshi",
      "time": "2026-07-01T00:10:00Z"
    },
    {
      "prop_type": "HR",
      "name": "Josh Bell",
      "opp_pitcher": "Mike Burrows",
      "team": "MIN",
      "opp": "HOU",
      "home": "HOU",
      "away": "MIN",
      "line": 0.5,
      "pick": "yes",
      "odds": "+1900",
      "model": 0.1772,
      "edge_val": 0.1282,
      "book": "Kalshi",
      "time": "2026-07-01T00:10:00Z"
    },
    {
      "prop_type": "HR",
      "name": "Griffin Conine",
      "opp_pitcher": "Tanner Gordon",
      "team": "MIA",
      "opp": "COL",
      "home": "COL",
      "away": "MIA",
      "line": 0.5,
      "pick": "yes",
      "odds": "+1329",
      "model": 0.1969,
      "edge_val": 0.1276,
      "book": "Kalshi",
      "time": "2026-07-01T00:40:00Z"
    },
    {
      "prop_type": "HR",
      "name": "Tristan Gray",
      "opp_pitcher": "Mike Burrows",
      "team": "MIN",
      "opp": "HOU",
      "home": "HOU",
      "away": "MIN",
      "line": 0.5,
      "pick": "yes",
      "odds": "+2400",
      "model": 0.1611,
      "edge_val": 0.1215,
      "book": "Kalshi",
      "time": "2026-07-01T00:10:00Z"
    },
    {
      "prop_type": "HR",
      "name": "Royce Lewis",
      "opp_pitcher": "Mike Burrows",
      "team": "MIN",
      "opp": "HOU",
      "home": "HOU",
      "away": "MIN",
      "line": 0.5,
      "pick": "yes",
      "odds": "+1150",
      "model": 0.1954,
      "edge_val": 0.1192,
      "book": "Kalshi",
      "time": "2026-07-01T00:10:00Z"
    },
    {
      "prop_type": "HR",
      "name": "Jake McCarthy",
      "opp_pitcher": "Eury P\u00e9rez",
      "team": "COL",
      "opp": "MIA",
      "home": "COL",
      "away": "MIA",
      "line": 0.5,
      "pick": "yes",
      "odds": "+2400",
      "model": 0.1484,
      "edge_val": 0.1088,
      "book": "Kalshi",
      "time": "2026-07-01T00:40:00Z"
    },
    {
      "prop_type": "HR",
      "name": "Victor Caratini",
      "opp_pitcher": "Mike Burrows",
      "team": "MIN",
      "opp": "HOU",
      "home": "HOU",
      "away": "MIN",
      "line": 0.5,
      "pick": "yes",
      "odds": "+2400",
      "model": 0.1445,
      "edge_val": 0.1049,
      "book": "Kalshi",
      "time": "2026-07-01T00:10:00Z"
    },
    {
      "prop_type": "HR",
      "name": "Kyle Stowers",
      "opp_pitcher": "Tanner Gordon",
      "team": "MIA",
      "opp": "COL",
      "home": "COL",
      "away": "MIA",
      "line": 0.5,
      "pick": "yes",
      "odds": "+1150",
      "model": 0.1758,
      "edge_val": 0.0996,
      "book": "Kalshi",
      "time": "2026-07-01T00:40:00Z"
    },
    {
      "prop_type": "HR",
      "name": "Seiya Suzuki",
      "opp_pitcher": "JP Sears",
      "team": "CHC",
      "opp": "SDP",
      "home": "CHC",
      "away": "SDP",
      "line": 0.5,
      "pick": "yes",
      "odds": "+1329",
      "model": 0.1544,
      "edge_val": 0.0871,
      "book": "Kalshi",
      "time": "2026-07-01T00:05:00Z"
    },
    {
      "prop_type": "HR",
      "name": "Xavier Edwards",
      "opp_pitcher": "Tanner Gordon",
      "team": "MIA",
      "opp": "COL",
      "home": "COL",
      "away": "MIA",
      "line": 0.5,
      "pick": "yes",
      "odds": "+2400",
      "model": 0.1244,
      "edge_val": 0.0848,
      "book": "Kalshi",
      "time": "2026-07-01T00:40:00Z"
    },
    {
      "prop_type": "HR",
      "name": "Samad Taylor",
      "opp_pitcher": "Matthew Boyd",
      "team": "SDP",
      "opp": "CHC",
      "home": "CHC",
      "away": "SDP",
      "line": 0.5,
      "pick": "yes",
      "odds": "+3233",
      "model": 0.1144,
      "edge_val": 0.0846,
      "book": "Kalshi",
      "time": "2026-07-01T00:05:00Z"
    },
    {
      "prop_type": "HR",
      "name": "Isaac Paredes",
      "opp_pitcher": "Joe Ryan",
      "team": "HOU",
      "opp": "MIN",
      "home": "HOU",
      "away": "MIN",
      "line": 0.5,
      "pick": "yes",
      "odds": "+2400",
      "model": 0.1221,
      "edge_val": 0.0825,
      "book": "Kalshi",
      "time": "2026-07-01T00:10:00Z"
    },
    {
      "prop_type": "HR",
      "name": "Michael Massey",
      "opp_pitcher": "Griffin Jax",
      "team": "KCR",
      "opp": "TBR",
      "home": "KCR",
      "away": "TBR",
      "line": 0.5,
      "pick": "yes",
      "odds": "+1329",
      "model": 0.1475,
      "edge_val": 0.0802,
      "book": "Kalshi",
      "time": "2026-06-30T23:40:00Z"
    },
    {
      "prop_type": "HR",
      "name": "Joe Mack",
      "opp_pitcher": "Tanner Gordon",
      "team": "MIA",
      "opp": "COL",
      "home": "COL",
      "away": "MIA",
      "line": 0.5,
      "pick": "yes",
      "odds": "+1567",
      "model": 0.1382,
      "edge_val": 0.0799,
      "book": "Kalshi",
      "time": "2026-07-01T00:40:00Z"
    },
    {
      "prop_type": "HR",
      "name": "Jose Altuve",
      "opp_pitcher": "Joe Ryan",
      "team": "HOU",
      "opp": "MIN",
      "home": "HOU",
      "away": "MIN",
      "line": 0.5,
      "pick": "yes",
      "odds": "+2400",
      "model": 0.1181,
      "edge_val": 0.0785,
      "book": "Kalshi",
      "time": "2026-07-01T00:10:00Z"
    },
    {
      "prop_type": "HR",
      "name": "Mookie Betts",
      "opp_pitcher": "Jeffrey Springs",
      "team": "LAD",
      "opp": "OAK",
      "home": "OAK",
      "away": "LAD",
      "line": 0.5,
      "pick": "yes",
      "odds": "+733",
      "model": 0.1929,
      "edge_val": 0.0752,
      "book": "Kalshi",
      "time": "2026-07-01T01:40:00Z"
    },
    {
      "prop_type": "HR",
      "name": "Kyle Karros",
      "opp_pitcher": "Eury P\u00e9rez",
      "team": "COL",
      "opp": "MIA",
      "home": "COL",
      "away": "MIA",
      "line": 0.5,
      "pick": "yes",
      "odds": "+1900",
      "model": 0.1142,
      "edge_val": 0.0652,
      "book": "Kalshi",
      "time": "2026-07-01T00:40:00Z"
    },
    {
      "prop_type": "HR",
      "name": "Miguel Andujar",
      "opp_pitcher": "Matthew Boyd",
      "team": "SDP",
      "opp": "CHC",
      "home": "CHC",
      "away": "SDP",
      "line": 0.5,
      "pick": "yes",
      "odds": "+2400",
      "model": 0.104,
      "edge_val": 0.0644,
      "book": "Kalshi",
      "time": "2026-07-01T00:05:00Z"
    },
    {
      "prop_type": "HR",
      "name": "J.P. Crawford",
      "opp_pitcher": "Jos\u00e9 Soriano",
      "team": "SEA",
      "opp": "LAA",
      "home": "SEA",
      "away": "LAA",
      "line": 0.5,
      "pick": "yes",
      "odds": "+1329",
      "model": 0.1303,
      "edge_val": 0.063,
      "book": "Kalshi",
      "time": "2026-07-01T01:40:00Z"
    },
    {
      "prop_type": "HR",
      "name": "Jakob Marsee",
      "opp_pitcher": "Tanner Gordon",
      "team": "MIA",
      "opp": "COL",
      "home": "COL",
      "away": "MIA",
      "line": 0.5,
      "pick": "yes",
      "odds": "+2400",
      "model": 0.1015,
      "edge_val": 0.0619,
      "book": "Kalshi",
      "time": "2026-07-01T00:40:00Z"
    },
    {
      "prop_type": "HR",
      "name": "Jung Hoo Lee",
      "opp_pitcher": "Brandon Pfaadt",
      "team": "SFG",
      "opp": "ARI",
      "home": "ARI",
      "away": "SFG",
      "line": 0.5,
      "pick": "yes",
      "odds": "+2400",
      "model": 0.1015,
      "edge_val": 0.0619,
      "book": "Kalshi",
      "time": "2026-07-01T01:40:00Z"
    },
    {
      "prop_type": "HR",
      "name": "Colt Emerson",
      "opp_pitcher": "Jos\u00e9 Soriano",
      "team": "SEA",
      "opp": "LAA",
      "home": "SEA",
      "away": "LAA",
      "line": 0.5,
      "pick": "yes",
      "odds": "+1329",
      "model": 0.1282,
      "edge_val": 0.0609,
      "book": "Kalshi",
      "time": "2026-07-01T01:40:00Z"
    },
    {
      "prop_type": "HR",
      "name": "Drew Gilbert",
      "opp_pitcher": "Brandon Pfaadt",
      "team": "SFG",
      "opp": "ARI",
      "home": "ARI",
      "away": "SFG",
      "line": 0.5,
      "pick": "yes",
      "odds": "+1900",
      "model": 0.1094,
      "edge_val": 0.0604,
      "book": "Kalshi",
      "time": "2026-07-01T01:40:00Z"
    },
    {
      "prop_type": "HR",
      "name": "Lane Thomas",
      "opp_pitcher": "Griffin Jax",
      "team": "KCR",
      "opp": "TBR",
      "home": "KCR",
      "away": "TBR",
      "line": 0.5,
      "pick": "yes",
      "odds": "+1329",
      "model": 0.1271,
      "edge_val": 0.0598,
      "book": "Kalshi",
      "time": "2026-06-30T23:40:00Z"
    },
    {
      "prop_type": "HR",
      "name": "Freddie Freeman",
      "opp_pitcher": "Jeffrey Springs",
      "team": "LAD",
      "opp": "OAK",
      "home": "OAK",
      "away": "LAD",
      "line": 0.5,
      "pick": "yes",
      "odds": "+614",
      "model": 0.1969,
      "edge_val": 0.0596,
      "book": "Kalshi",
      "time": "2026-07-01T01:40:00Z"
    },
    {
      "prop_type": "HR",
      "name": "Ezequiel Tovar",
      "opp_pitcher": "Eury P\u00e9rez",
      "team": "COL",
      "opp": "MIA",
      "home": "COL",
      "away": "MIA",
      "line": 0.5,
      "pick": "yes",
      "odds": "+1567",
      "model": 0.1163,
      "edge_val": 0.0581,
      "book": "Kalshi",
      "time": "2026-07-01T00:40:00Z"
    },
    {
      "prop_type": "HR",
      "name": "Ty France",
      "opp_pitcher": "Matthew Boyd",
      "team": "SDP",
      "opp": "CHC",
      "home": "CHC",
      "away": "SDP",
      "line": 0.5,
      "pick": "yes",
      "odds": "+1329",
      "model": 0.1229,
      "edge_val": 0.0536,
      "book": "Kalshi",
      "time": "2026-07-01T00:05:00Z"
    },
    {
      "prop_type": "HR",
      "name": "Edouard Julien",
      "opp_pitcher": "Eury P\u00e9rez",
      "team": "COL",
      "opp": "MIA",
      "home": "COL",
      "away": "MIA",
      "line": 0.5,
      "pick": "yes",
      "odds": "+1900",
      "model": 0.1024,
      "edge_val": 0.0534,
      "book": "Kalshi",
      "time": "2026-07-01T00:40:00Z"
    },
    {
      "prop_type": "HR",
      "name": "Xander Bogaerts",
      "opp_pitcher": "Matthew Boyd",
      "team": "SDP",
      "opp": "CHC",
      "home": "CHC",
      "away": "SDP",
      "line": 0.5,
      "pick": "yes",
      "odds": "+1900",
      "model": 0.1017,
      "edge_val": 0.0527,
      "book": "Kalshi",
      "time": "2026-07-01T00:05:00Z"
    }
  ]
}